aws_cdk_microservice/__init__.py
aws_cdk_microservice/py.typed
aws_cdk_microservice/_jsii/__init__.py
aws_cdk_microservice/_jsii/aws-cdk-microservice@0.0.19.jsii.tgz
aws_cdk_microservice-0.0.19.dist-info/LICENSE
aws_cdk_microservice-0.0.19.dist-info/METADATA
aws_cdk_microservice-0.0.19.dist-info/WHEEL
aws_cdk_microservice-0.0.19.dist-info/top_level.txt
aws_cdk_microservice-0.0.19.dist-info/RECORD
