Metadata-Version: 2.1
Name: aws-cdk-microservice
Version: 0.0.19
Summary: @smallcase/aws-cdk-microservice
Home-page: https://github.com/smallcase/aws-cdk-microservice.git
Author: Gagan Singh<gaganpreet.singh@smallcase.com>
License: Apache-2.0
Project-URL: Source, https://github.com/smallcase/aws-cdk-microservice.git
Platform: UNKNOWN
Classifier: Intended Audience :: Developers
Classifier: Operating System :: OS Independent
Classifier: Programming Language :: JavaScript
Classifier: Programming Language :: Python :: 3 :: Only
Classifier: Programming Language :: Python :: 3.6
Classifier: Programming Language :: Python :: 3.7
Classifier: Programming Language :: Python :: 3.8
Classifier: Programming Language :: Python :: 3.9
Classifier: Typing :: Typed
Classifier: Development Status :: 5 - Production/Stable
Classifier: License :: OSI Approved
Requires-Python: >=3.6
License-File: LICENSE
Requires-Dist: aws-cdk-lib (==2.8.0)
Requires-Dist: constructs (<11.0.0,>=10.0.5)
Requires-Dist: jsii (<2.0.0,>=1.54.0)
Requires-Dist: publication (>=0.0.3)
